lingua/__init__.py
lingua/hooks.py
lingua/lingua_sdk.py
lingua/utils.py
pylingua-0.3.0.dist-info/LICENSE
pylingua-0.3.0.dist-info/METADATA
pylingua-0.3.0.dist-info/WHEEL
pylingua-0.3.0.dist-info/top_level.txt
pylingua-0.3.0.dist-info/RECORD
