Metadata-Version: 2.1
Name: pylingua
Version: 0.3.0
Summary: A user toolkit for analyzing and interfacing with Large Language Models (LLMs)
Home-page: https://github.com/VectorInstitute/lingua-sdk
Author: ['Vector AI Engineering']
Author-email: ai_engineering@vectorinstitute.ai
License: MIT
Keywords: python nlp machine-learning deep-learning distributed-computing neural-networks tensor llm
Platform: UNKNOWN
Classifier: Development Status :: 3 - Alpha
Classifier: Intended Audience :: Science/Research
Classifier: Intended Audience :: Developers
Classifier: License :: OSI Approved :: MIT License
Classifier: Operating System :: POSIX :: Linux
Classifier: Programming Language :: Python :: 3.8
Classifier: Programming Language :: Python :: 3.9
Classifier: Programming Language :: Python :: 3.10
Classifier: Programming Language :: Python :: 3.11
Classifier: Programming Language :: Python :: 3.12
License-File: LICENSE
Requires-Dist: certifi (==2022.12.7)
Requires-Dist: charset-normalizer (==3.0.1)
Requires-Dist: idna (==3.4)
Requires-Dist: requests (==2.28.2)
Requires-Dist: torch (==1.13.1)
Requires-Dist: typing-extensions (==4.4.0)
Requires-Dist: urllib3 (==1.26.14)
Requires-Dist: numpy
